libname/__init__.py
libname/hello.py
helloex1-0.0.1.dist-info/METADATA
helloex1-0.0.1.dist-info/WHEEL
helloex1-0.0.1.dist-info/top_level.txt
helloex1-0.0.1.dist-info/RECORD
